capuccino/__init__.py
capuccino-0.0.1.dist-info/LICENCE.txt
capuccino-0.0.1.dist-info/METADATA
capuccino-0.0.1.dist-info/WHEEL
capuccino-0.0.1.dist-info/top_level.txt
capuccino-0.0.1.dist-info/RECORD
