Metadata-Version: 2.1
Name: capuccino
Version: 0.0.1
Summary: Library to help python developers wtih sql server connections
Home-page: UNKNOWN
Author: Silvio Lacerda
Author-email: silviolacerda21@gmail.com
License: MIT
Keywords: sql server
Platform: UNKNOWN
Classifier: Programming Language :: Python :: 2
Classifier: License :: OSI Approved :: MIT License
Classifier: Operating System :: OS Independent
Requires-Dist: pyodbc
Requires-Dist: pandas
